crack-engine/__init__.py
crackengine/__init__.py
crack_engine_CraXell-0.0.1.2.dist-info/LICENSE
crack_engine_CraXell-0.0.1.2.dist-info/METADATA
crack_engine_CraXell-0.0.1.2.dist-info/WHEEL
crack_engine_CraXell-0.0.1.2.dist-info/top_level.txt
crack_engine_CraXell-0.0.1.2.dist-info/RECORD
