Metadata-Version: 2.1
Name: crack-engine-CraXell
Version: 0.0.1.2
Summary: A package
Home-page: https://github.com/CraXell/crack-engine
Author: CraXell
Author-email: craxell.tv@gmail.com
License: UNKNOWN
Platform: UNKNOWN
Classifier: Programming Language :: Python :: 3
Classifier: Operating System :: OS Independent
Requires-Python: >=3.6
